doubao_config
